dvg_randomizer/__main__.py
dvg_randomizer/aircraft.py
dvg_randomizer/boardgame.py
dvg_randomizer/campaign.py
dvg_randomizer/config.py
dvg_randomizer/data.py
dvg_randomizer/dvg.ods
dvg_randomizer/game.py
dvg_randomizer/logger.py
dvg_randomizer/logsheet.py
dvg_randomizer/pilot.py
dvg_randomizer/gui/composition.py
dvg_randomizer/gui/main.py
dvg_randomizer/misc/DejaVuSansCondensed.ttf
dvg_randomizer-1.4.3.dist-info/COPYING
dvg_randomizer-1.4.3.dist-info/LICENSE
dvg_randomizer-1.4.3.dist-info/METADATA
dvg_randomizer-1.4.3.dist-info/WHEEL
dvg_randomizer-1.4.3.dist-info/entry_points.txt
dvg_randomizer-1.4.3.dist-info/top_level.txt
dvg_randomizer-1.4.3.dist-info/RECORD
