Metadata-Version: 2.1
Name: dvg-randomizer
Version: 1.4.3
Summary: Randomizer app for DVG Leader boardgames
Author-email: Jerome Quelin <jquelin@gmail.com>
Project-URL: Homepage, https://github.com/jquelin/dvg-randomize
Project-URL: Bug Tracker, https://github.com/jquelin/dvg-randomize/issues
Classifier: Programming Language :: Python :: 3
Classifier: License :: OSI Approved :: GNU General Public License v3 or later (GPLv3+)
Classifier: Operating System :: OS Independent
Requires-Python: >=3.7
License-File: LICENSE
License-File: COPYING
Requires-Dist: appdirs
Requires-Dist: colorlog
Requires-Dist: fpdf
Requires-Dist: pyexcel-ods
Requires-Dist: pyyaml
Requires-Dist: cmd2
